{
    "data": [
                {
                  "address": "R/o Kochupidikayil, Thaslim Manzil, Marakkarkandi, Kannur",
                  "aliases": "Ayub",
                  "image_url": "https://nia.gov.in/writereaddata/Portal/Wanted/528_1_1_1.jpg",
                  "name": "Mohd Sabir",
                  "organization": "Jihadi"
                },
                {
                  "address": "R/o Baitul Mujahideen of LeT training camp, Muzaffrabad, Pak occupied Kashmir",
                  "aliases": "Abdul Aziz @ Rashid Abdullah @ Abdrehan",
                  "image_url": "https://nia.gov.in/writereaddata/Portal/Wanted/529_1_1_imgnotavailable.jpg",
                  "name": "Wali",
                  "organization": "Jihadi"
                },
                {
                  "address": "R/o Baitul Mujahideen of LeT training camp, Muzaffrabad, Pak occupied Kashmir",
                  "aliases": "Abdul Aziz @ Rashid Abdullah @ Abdrehan",
                  "image_url": "https://nia.gov.in/writereaddata/Portal/Wanted/529_1_1_imgnotavailable.jpg",
                  "name": "Wali",
                  "organization": "Jihadi"
                },
                {
                  "address": "Araf Villa, Opp. Sunni Centre, Mullur, Udupi, Karnataka",
                  "aliases": "Moideenabba Ummar Byari",
                  "image_url": "https://nia.gov.in/writereaddata/Portal/Wanted/532_1_1_5.jpg",
                  "name": "Moideen",
                  "organization": "FICN"
                },
                {
                  "address": "Araf Villa, Opp. Sunni Centre, Mullur, Udupi, Karnataka",
                  "aliases": "Moideenabba Ummar Byari",
                  "image_url": "https://nia.gov.in/writereaddata/Portal/Wanted/532_1_1_5.jpg",
                  "name": "Moideen",
                  "organization": "FICN"
                },
                {
                  "address": "Ambedkar Colony, Opposite to Hanumavva Doothara Mada, Kurudi Maine Road. Aroli Post, Aroli Village, Manvi PS limit, Raichur District, Karnataka",
                  "aliases": "Jayanna @ John @ Marappa",
                  "image_url": "https://nia.gov.in/writereaddata/Portal/Wanted/534_1_1_7.jpg",
                  "name": "Mahesh",
                  "organization": "Left Wing Extremism"
                },
                {
                  "address": "Kotyantadka House, Kuthlur P.O, Kuthlur Village, Belthangadi Taluk, Venoor P.S, Dakshina Kannada District, Karnataka",
                  "aliases": "",
                  "image_url": "https://nia.gov.in/writereaddata/Portal/Wanted/535_1_1_8.jpg",
                  "name": "Sundari",
                  "organization": "Left Wing Extremism"
                },
                {
                  "address": "Kotyantadka House, Kuthlur P.O, Kuthlur Village, Belthangadi Taluk, Venoor P.S, Dakshina Kannada District, Karnataka",
                  "aliases": "",
                  "image_url": "https://nia.gov.in/writereaddata/Portal/Wanted/535_1_1_8.jpg",
                  "name": "Sundari",
                  "organization": "Left Wing Extremism"
                },
                {
                  "address": "Kotyantadka House, Kuthlur P.O, Kuthlur Village, Belthangadi Taluk, Venoor P.S, Dakshina Kannada District, Karnataka",
                  "aliases": "",
                  "image_url": "https://nia.gov.in/writereaddata/Portal/Wanted/535_1_1_8.jpg",
                  "name": "Sundari",
                  "organization": "Left Wing Extremism"
                },
                {
                  "address": "R/o XVII/368, Kannamangalam Road, Maithani, Elambachi, Near Ramalvilayam Pazhakam, South Trikaripur, Hosdurg Taluk, Chandera PS, Kasaragod",
                  "aliases": "",
                  "image_url": "https://nia.gov.in/writereaddata/Portal/Wanted/538_1_1_111.jpg",
                  "name": "Firoskhan M.T.P.",
                  "organization": "Jihadi"
                },
                {
                  "address": "R/o XVII/368, Kannamangalam Road, Maithani, Elambachi, Near Ramalvilayam Pazhakam, South Trikaripur, Hosdurg Taluk, Chandera PS, Kasaragod",
                  "aliases": "",
                  "image_url": "https://nia.gov.in/writereaddata/Portal/Wanted/538_1_1_111.jpg",
                  "name": "Firoskhan M.T.P.",
                  "organization": "Jihadi"
                },
                {
                  "address": "R/o Haji Abdul Majeed House, Panchayat Road, Thekkepuram, Padne P.O. Near Padanna Petrol Pump, Padanna, Kasaragod",
                  "aliases": "",
                  "image_url": "https://nia.gov.in/writereaddata/Portal/Wanted/540_1_1_131.jpg",
                  "name": "Ashfak Majeed Kallu kettiya Purayil",
                  "organization": "Jihadi"
                },
                {
                  "address": "R/o Haji Abdul Majeed House, Panchayat Road, Thekkepuram, Padne P.O. Near Padanna Petrol Pump, Padanna, Kasaragod",
                  "aliases": "",
                  "image_url": "https://nia.gov.in/writereaddata/Portal/Wanted/540_1_1_131.jpg",
                  "name": "Ashfak Majeed Kallu kettiya Purayil",
                  "organization": "Jihadi"
                },
                {
                  "address": "R/o Kalavarapa-rambil House, Murikkavu, Yakkara, Mangalam Dam P.O., Palakkad",
                  "aliases": "@ Isa @ Easa",
                  "image_url": "https://nia.gov.in/writereaddata/Portal/Wanted/542_1_1_151.jpg",
                  "name": "Bexen Vincent",
                  "organization": "Jihadi"
                },
                {
                  "address": "R/o Kalavarapa-rambil House, Murikkavu, Yakkara, Mangalam Dam P.O., Palakkad",
                  "aliases": "@ Isa @ Easa",
                  "image_url": "https://nia.gov.in/writereaddata/Portal/Wanted/542_1_1_151.jpg",
                  "name": "Bexen Vincent",
                  "organization": "Jihadi"
                },
                {
                  "address": "R/o Kalavaraparambil House, Murikkavu, Yakkara, Palakkad.",
                  "aliases": "Mariyam",
                  "image_url": "https://nia.gov.in/writereaddata/Portal/Wanted/544_1_1_17.jpg",
                  "name": "Merrin Jacob Pallath",
                  "organization": "Jihadi"
                },
                {
                  "address": "R/o Kalavaraparambil House, Murikkavu, Yakkara, Palakkad.",
                  "aliases": "Mariyam",
                  "image_url": "https://nia.gov.in/writereaddata/Portal/Wanted/544_1_1_17.jpg",
                  "name": "Merrin Jacob Pallath",
                  "organization": "Jihadi"
                },
                {
                  "address": "A K, Zainabas, Near Mannam Mini Stadium, Valapattanam, PO, Kannur",
                  "aliases": "",
                  "image_url": "https://nia.gov.in/writereaddata/Portal/Wanted/547_1_1_20.jpg",
                  "name": "Muhammed Rishal K",
                  "organization": "-"
                },
                {
                  "address": "A K, Zainabas, Near Mannam Mini Stadium, Valapattanam, PO, Kannur",
                  "aliases": "",
                  "image_url": "https://nia.gov.in/writereaddata/Portal/Wanted/547_1_1_20.jpg",
                  "name": "Muhammed Rishal K",
                  "organization": "-"
                },
                {
                  "address": "A K, Zainabas, Near Mannam Mini Stadium, Valapattanam, PO, Kannur",
                  "aliases": "",
                  "image_url": "https://nia.gov.in/writereaddata/Portal/Wanted/547_1_1_20.jpg",
                  "name": "Muhammed Rishal K",
                  "organization": "-"
                },
                {
                  "address": "",
                  "aliases": "Mohamed Hussain Hussaine @ Hssaiane Raas",
                  "image_url": "https://nia.gov.in/writereaddata/Portal/Wanted/550_1_1_imgnotavailable.jpg",
                  "name": "Mohamed Sulaiman",
                  "organization": "Others"
                },
                {
                  "address": "",
                  "aliases": "Mohamed Hussain Hussaine @ Hssaiane Raas",
                  "image_url": "https://nia.gov.in/writereaddata/Portal/Wanted/550_1_1_imgnotavailable.jpg",
                  "name": "Mohamed Sulaiman",
                  "organization": "Others"
                },
                {
                  "address": "",
                  "aliases": "Mohamed Hussain Hussaine @ Hssaiane Raas",
                  "image_url": "https://nia.gov.in/writereaddata/Portal/Wanted/550_1_1_imgnotavailable.jpg",
                  "name": "Mohamed Sulaiman",
                  "organization": "Others"
                },
                {
                  "address": "",
                  "aliases": "Mohamed Hussain Hussaine @ Hssaiane Raas",
                  "image_url": "https://nia.gov.in/writereaddata/Portal/Wanted/550_1_1_imgnotavailable.jpg",
                  "name": "Mohamed Sulaiman",
                  "organization": "Others"
                },
                {
                  "address": "R/o Rosounchouk Village, Chapainawabganj, Distt- Bangladesh",
                  "aliases": "Alim Sk",
                  "image_url": "https://nia.gov.in/writereaddata/Portal/Wanted/555_1_1_28.jpg",
                  "name": "Alim Sheik",
                  "organization": "-"
                },
                {
                  "address": "R/o Ayisha Manzil, North Paravoor, Ernakulam",
                  "aliases": "",
                  "image_url": "https://nia.gov.in/writereaddata/Portal/Wanted/556_1_1_imgnotavailable.jpg",
                  "name": "Hasir Uchummal Mohammad (A-1)",
                  "organization": "-"
                },
                {
                  "address": "R/o Kottakal,,Malapuram, Kerala",
                  "aliases": "Sidhikul Akbar",
                  "image_url": "https://nia.gov.in/writereaddata/Portal/Wanted/557_1_1_imgnotavailable.jpg",
                  "name": "Siddique (A-2)",
                  "organization": "-"
                },
                {
                  "address": "R/o 109, MarnamiByle, Shimoga, Karnataka",
                  "aliases": "",
                  "image_url": "https://nia.gov.in/writereaddata/Portal/Wanted/558_1_1_31.jpg",
                  "name": "Taha Mohammed",
                  "organization": "-"
                },
                {
                  "address": "R/o Kodiyathur, Gothamb Road, Near Mujahid Mosque, Mukkam, Kozhikode, Kerala",
                  "aliases": "",
                  "image_url": "https://nia.gov.in/writereaddata/Portal/Wanted/559_1_1_32.jpg",
                  "name": "Sultan Abdulla",
                  "organization": "-"
                },
                {
                  "address": "R/o Pulluttiparambil House, Nattika, PO Trissur, Kerala",
                  "aliases": "",
                  "image_url": "https://nia.gov.in/writereaddata/Portal/Wanted/560_1_1_33.jpg",
                  "name": "Fayez Farooq",
                  "organization": "-"
                }
              ]
              
            
        }